calculator_server.py
isuru211_calculator_mcp_server-1.0.0.dist-info/licenses/LICENSE
isuru211_calculator_mcp_server-1.0.0.dist-info/METADATA
isuru211_calculator_mcp_server-1.0.0.dist-info/WHEEL
isuru211_calculator_mcp_server-1.0.0.dist-info/entry_points.txt
isuru211_calculator_mcp_server-1.0.0.dist-info/top_level.txt
isuru211_calculator_mcp_server-1.0.0.dist-info/RECORD
