Metadata-Version: 2.4
Name: isuru211-calculator-mcp-server
Version: 1.0.0
Summary: A server for complex mathematical calculations
Requires-Python: >=3.9
License-File: LICENSE
Requires-Dist: fastmcp>=0.4.1
Requires-Dist: numpy>=2.2.0
Requires-Dist: scipy>=1.15.0
Requires-Dist: sympy>=1.13.0
Requires-Dist: matplotlib
Requires-Dist: pydantic>=2.10.0
Provides-Extra: dev
Requires-Dist: pytest>=8.3.0; extra == "dev"
Dynamic: license-file
